godot_project_parser/__init__.py
godot_project_parser/_dump.py
godot_project_parser/_parser.py
godot_project_parser/types.py
godot_project_parser-0.1.0.dist-info/LICENSE
godot_project_parser-0.1.0.dist-info/METADATA
godot_project_parser-0.1.0.dist-info/WHEEL
godot_project_parser-0.1.0.dist-info/entry_points.txt
godot_project_parser-0.1.0.dist-info/RECORD
