Metadata-Version: 2.2
Name: godot-project-parser
Version: 0.1.0
Summary: Parser and editor of project.godot files.
Author-email: Dominic Davis-Foster <dominic@davis-foster.co.uk>
License: MIT
Home-page: https://github.com/potbanksoftware/godot-project-parser
Project-URL: Issue Tracker, https://github.com/potbanksoftware/godot-project-parser/issues
Project-URL: Source Code, https://github.com/potbanksoftware/godot-project-parser
Project-URL: Documentation, https://godot-project-parser.readthedocs.io/en/latest
Platform: Windows
Platform: macOS
Platform: Linux
Classifier: License :: OSI Approved :: MIT License
Classifier: Operating System :: OS Independent
Classifier: Programming Language :: Python
Classifier: Programming Language :: Python :: 3 :: Only
Classifier: Programming Language :: Python :: 3.8
Classifier: Programming Language :: Python :: 3.9
Classifier: Programming Language :: Python :: 3.10
Classifier: Programming Language :: Python :: 3.11
Classifier: Programming Language :: Python :: 3.12
Classifier: Programming Language :: Python :: Implementation :: CPython
Requires-Python: >=3.8
Requires-Dist: tomli>=2.2.1
